[
    {
        "key": "datr",
        "value": "TbK2aWe7q83AqqADUe0HnB52",
        "domain": "facebook.com",
        "path": "/",
        "hostOnly": false,
        "creation": "2026-03-16T09:20:57.378Z",
        "lastAccessed": "2026-03-16T09:20:57.379Z"
    },
    {
        "key": "sb",
        "value": "TrK2aQLb1q7i7ACXVp6xyINi",
        "domain": "facebook.com",
        "path": "/",
        "hostOnly": false,
        "creation": "2026-03-16T09:20:57.379Z",
        "lastAccessed": "2026-03-16T09:20:57.379Z"
    },
    {
        "key": "locale",
        "value": "zh_CN",
        "domain": "facebook.com",
        "path": "/",
        "hostOnly": false,
        "creation": "2026-03-16T09:20:57.379Z",
        "lastAccessed": "2026-03-16T09:20:57.379Z"
    },
    {
        "key": "pas",
        "value": "61552622404538%3A7MSS6iqOjI",
        "domain": "facebook.com",
        "path": "/",
        "hostOnly": false,
        "creation": "2026-03-16T09:20:57.379Z",
        "lastAccessed": "2026-03-16T09:20:57.379Z"
    },
    {
        "key": "wl_cbv",
        "value": "v2%3Bclient_version%3A3112%3Btimestamp%3A1773581010",
        "domain": "facebook.com",
        "path": "/",
        "hostOnly": false,
        "creation": "2026-03-16T09:20:57.379Z",
        "lastAccessed": "2026-03-16T09:20:57.379Z"
    },
    {
        "key": "vpd",
        "value": "v1%3B836x427x1.6875",
        "domain": "facebook.com",
        "path": "/",
        "hostOnly": false,
        "creation": "2026-03-16T09:20:57.379Z",
        "lastAccessed": "2026-03-16T09:20:57.379Z"
    },
    {
        "key": "fr",
        "value": "06kmzWblyPG1marvP.AWco4LU1cbirGoSPThuYHqzHrW-ZU2O7ocL-LVzk_e8VgUZkpqw.BptrJO..AAA.0.0.Bpt8st.AWeLlIi2akbxFSwx8rxWw9h6-uk",
        "domain": "facebook.com",
        "path": "/",
        "hostOnly": false,
        "creation": "2026-03-16T09:20:57.379Z",
        "lastAccessed": "2026-03-16T09:20:57.379Z"
    }
]
